openflam/__init__.py
openflam/hook.py
openflam/module/contrastive_loss.py
openflam/module/feature_fusion.py
openflam/module/htsat.py
openflam/module/model.py
openflam/module/plot_utils.py
openflam-1.0.1.dist-info/licenses/LICENSE
openflam-1.0.1.dist-info/METADATA
openflam-1.0.1.dist-info/WHEEL
openflam-1.0.1.dist-info/top_level.txt
openflam-1.0.1.dist-info/RECORD
