Metadata-Version: 2.4
Name: openflam
Version: 1.0.1
Summary: Framewise Lanaguge-Audio Modeling
Author: Yusong Wu
Author-email: Ke Chen <kechen@adobe.com>, Oriol Nieto <onieto@adobe.com>, Prem Seetharaman <seethara@adobe.com>
Maintainer: Yusong Wu
Maintainer-email: Ke Chen <kechen@adobe.com>, Oriol Nieto <onieto@adobe.com>, Prem Seetharaman <seethara@adobe.com>
License: Copyright © 2025, Adobe Inc. and its licensors. All rights reserved.
Project-URL: Homepage, https://github.com/adobe-research/openflam
Project-URL: Bug Tracker, https://github.com/adobe-research/openflam/issues
Classifier: Development Status :: 3 - Alpha
Classifier: Intended Audience :: Developers
Classifier: Intended Audience :: Science/Research
Classifier: License :: OSI Approved :: Apache Software License
Classifier: Topic :: Scientific/Engineering :: Artificial Intelligence
Requires-Python: >=3.10
License-File: LICENSE
Requires-Dist: numpy<2.0.0,>=1.23.5
Requires-Dist: soundfile
Requires-Dist: librosa
Requires-Dist: torchlibrosa
Requires-Dist: torch<2.8.0,>=2.6.0
Requires-Dist: torchaudio<2.8.0,>=2.6.0
Requires-Dist: torchvision<0.23.0,>=0.21.0
Requires-Dist: lightning
Requires-Dist: transformers==4.56.1
Requires-Dist: matplotlib
Dynamic: license-file
